__init__.py
impulse/__init__.py
impulse/contracts_client/__init__.py
impulse/contracts_client/cli_utils.py
impulse/contracts_client/client.py
impulse/contracts_client/compute_power.py
impulse/contracts_client/config.py
impulse/contracts_client/constants.py
impulse/contracts_client/error_handler.py
impulse/contracts_client/event_handler.py
impulse/contracts_client/node_client.py
impulse/contracts_client/user_client.py
impulse/contracts_client/utils.py
impulse_contracts_client-0.4.0.dist-info/licenses/LICENSE.md
impulse_contracts_client-0.4.0.dist-info/METADATA
impulse_contracts_client-0.4.0.dist-info/WHEEL
impulse_contracts_client-0.4.0.dist-info/entry_points.txt
impulse_contracts_client-0.4.0.dist-info/top_level.txt
impulse_contracts_client-0.4.0.dist-info/RECORD
