Metadata-Version: 2.4
Name: impulse-contracts-client
Version: 0.4.0
Summary: Client for interacting with the Impulse Labs protocol
Home-page: https://github.com/impulselabs/contracts-client
Author: Impulse Labs AI
Author-email: engg@impulselabs.ai
License: MIT
Requires-Python: >=3.12
License-File: LICENSE.md
Requires-Dist: web3
Requires-Dist: eth-account
Requires-Dist: eth-typing
Requires-Dist: python-dotenv
Requires-Dist: eth_abi
Requires-Dist: click
Requires-Dist: pytest
Requires-Dist: setuptools
Requires-Dist: pynvml
Requires-Dist: psutil
Dynamic: author
Dynamic: author-email
Dynamic: description
Dynamic: description-content-type
Dynamic: home-page
Dynamic: license
Dynamic: license-file
Dynamic: requires-dist
Dynamic: requires-python
Dynamic: summary
